deceptionlogic_ai/__init__.py
deceptionlogic_ai/configuration.py
deceptionlogic_ai/deploy_agent.py
deceptionlogic_ai/llm_client.py
deceptionlogic_ai/load_app.py
deceptionlogic_ai/main.py
deceptionlogic_ai/utils.py
delo_mcp_client/__init__.py
delo_mcp_client/configuration.py
delo_mcp_client/deploy_agent.py
delo_mcp_client/llm_client.py
delo_mcp_client/load_app.py
delo_mcp_client/main.py
delo_mcp_client/utils.py
deceptionlogic_ai-0.1.1.dist-info/METADATA
deceptionlogic_ai-0.1.1.dist-info/WHEEL
deceptionlogic_ai-0.1.1.dist-info/entry_points.txt
deceptionlogic_ai-0.1.1.dist-info/top_level.txt
deceptionlogic_ai-0.1.1.dist-info/RECORD
